awsmon/__init__.py
awsmon/main.py
awsmon/models/__init__.py
awsmon/models/stack.py
awsmon/models/stacklist.py
awsmon/services/__init__.py
awsmon/services/argument_parser.py
awsmon/services/aws_service.py
awsmon/services/cache.py
awsmon/services/notifier.py
awsmon-0.0.1.dist-info/METADATA
awsmon-0.0.1.dist-info/WHEEL
awsmon-0.0.1.dist-info/entry_points.txt
awsmon-0.0.1.dist-info/top_level.txt
awsmon-0.0.1.dist-info/RECORD
