Metadata-Version: 2.1
Name: awsmon
Version: 0.0.1
Summary: Monitor AWS cloudformation stacks and notify on macos any status change
Home-page: https://www.github.com/sergiopena/awsmon
Author: Sergio Pena
Author-email: isergiopena@gmail.com
License: BSD
Keywords: aws cloudformation monitor macos notify
Platform: UNKNOWN
Classifier: Development Status :: 3 - Alpha
Classifier: Topic :: Utilities
Classifier: License :: OSI Approved :: BSD License
Requires-Dist: boto3 (==1.23.6)
Requires-Dist: pydantic (==1.10.0a1)
